LICENSE
README.md
setup.py
mpi4py_installer/__init__.py
mpi4py_installer/__main__.py
mpi4py_installer/cli.py
mpi4py_installer/runners.py
mpi4py_installer.egg-info/PKG-INFO
mpi4py_installer.egg-info/SOURCES.txt
mpi4py_installer.egg-info/dependency_links.txt
mpi4py_installer.egg-info/top_level.txt
mpi4py_installer/sites/__init__.py
mpi4py_installer/sites/nersc.py