Metadata-Version: 2.1
Name: mpi4py-installer
Version: 0.3.1
Summary: No more copy+paste of magic bash commands while installing mpi4py on HPC systems.
Home-page: https://github.com/JBlaschke/mpi4py-installer
Author: Johannes Blaschke
Author-email: jblaschke@lbl.gov
Classifier: Programming Language :: Python :: 3
Classifier: License :: OSI Approved :: MIT License
Classifier: Operating System :: OS Independent
Requires-Python: >=3.6
License-File: LICENSE
